dwave/plugins/__init__.py
dwave/plugins/sklearn/__init__.py
dwave/plugins/sklearn/transformers.py
dwave/plugins/sklearn/utilities.py
dwave_scikit_learn_plugin-0.2.0.dist-info/licenses/LICENSE
dwave_scikit_learn_plugin-0.2.0.dist-info/METADATA
dwave_scikit_learn_plugin-0.2.0.dist-info/WHEEL
dwave_scikit_learn_plugin-0.2.0.dist-info/top_level.txt
dwave_scikit_learn_plugin-0.2.0.dist-info/RECORD
