Metadata-Version: 2.4
Name: dwave-scikit-learn-plugin
Version: 0.2.0
Summary: A plugin to scikit-learn for quantum-classical hybrid solving.
Author-email: "D-Wave Inc." <tools@dwavesys.com>
License-Expression: Apache-2.0
Project-URL: Homepage, https://github.com/dwavesystems/dwave-scikit-learn-plugin
Project-URL: Download, https://github.com/dwavesystems/dwave-scikit-learn-plugin/releases
Classifier: Operating System :: OS Independent
Classifier: Programming Language :: Python
Classifier: Programming Language :: Python :: 3
Requires-Python: >=3.9
License-File: LICENSE
Requires-Dist: dimod>=0.12.20
Requires-Dist: dwave-optimization>=0.6.2
Requires-Dist: dwave-system>=1.32.0
Requires-Dist: numpy>=2.0.2
Requires-Dist: scikit-learn>=1.6.1
Dynamic: license-file
